base_aux/__init__.py
base_aux/test__init_tests.py
base_aux/_0_EXAMPLES_EXPLORE/__init__.py
base_aux/_0_EXAMPLES_EXPLORE/_explore.py
base_aux/_0_EXAMPLES_EXPLORE/main.py
base_aux/_0_EXAMPLES_EXPLORE/test_0_lambda_tricks.py
base_aux/_0_EXAMPLES_EXPLORE/test_0_operations.py
base_aux/_0_EXAMPLES_EXPLORE/test_1_funcs.py
base_aux/_0_EXAMPLES_EXPLORE/test_2_cls.py
base_aux/_0_EXAMPLES_EXPLORE/test_3_aio.py
base_aux/alerts/_PROJECT.py
base_aux/alerts/__init__.py
base_aux/alerts/_examples.py
base_aux/alerts/_test__1_alerts.py
base_aux/alerts/m1_alert0_base.py
base_aux/alerts/m1_alerts1_smtp.py
base_aux/alerts/m1_alerts2_telegram.py
base_aux/alerts/m2_select.py
base_aux/aux_argskwargs/__init__.py
base_aux/aux_argskwargs/m1_argskwargs.py
base_aux/aux_argskwargs/m2_argskwargs_aux.py
base_aux/aux_argskwargs/m3_args_bool_raise_if.py
base_aux/aux_argskwargs/m4_kwargs_eq_expect.py
base_aux/aux_argskwargs/test_2__kwargs_aux.py
base_aux/aux_argskwargs/test_3__bool_raise_if.py
base_aux/aux_argskwargs/test_4__kwargs_eq_expect.py
base_aux/aux_attr/__init__.py
base_aux/aux_attr/_m4_kits2_stable_keyset.py
base_aux/aux_attr/_test_4_kits2_stableKeySet.py
base_aux/aux_attr/m0_static.py
base_aux/aux_attr/m1_annot_attr1_aux.py
base_aux/aux_attr/m2_annot3_gacls_keys_as_values.py
base_aux/aux_attr/m3_ga0_echo.py
base_aux/aux_attr/m3_ga1_prefix_1_inst.py
base_aux/aux_attr/m3_ga1_prefix_2_cls.py
base_aux/aux_attr/m4_dump0_dumped.py
base_aux/aux_attr/m4_dump1_dumping1_dict.py
base_aux/aux_attr/m4_kits.py
base_aux/aux_attr/m5_attr_diff.py
base_aux/aux_attr/test_0__static.py
base_aux/aux_attr/test_1__attr1_attr.py
base_aux/aux_attr/test_1__attr2_annot1_iter.py
base_aux/aux_attr/test_1__attr2_annot2_other.py
base_aux/aux_attr/test_2__annot4_cls_keys_as_values.py
base_aux/aux_attr/test_3__getattr0_echo.py
base_aux/aux_attr/test_3__getattr3_prefix_1_inst.py
base_aux/aux_attr/test_3__getattr3_prefix_1_inst_raiseif.py
base_aux/aux_attr/test_4__dump_dumping.py
base_aux/aux_attr/test_4__kits.py
base_aux-0.3.12.dist-info/LICENSE
base_aux-0.3.12.dist-info/LICENSE_bundled.md
base_aux-0.3.12.dist-info/METADATA
base_aux-0.3.12.dist-info/WHEEL
base_aux-0.3.12.dist-info/top_level.txt
base_aux-0.3.12.dist-info/RECORD
