Metadata-Version: 2.1
Name: base_aux
Version: 0.3.12
Summary: collect all my previous modules in one package
Home-page: https://github.com/centroid457/
Author: Andrei Starichenko
Author-email: centroid@mail.ru
Project-URL: NestInit_Source, https://github.com/centroid457/base_aux
Classifier: Topic :: Software Development :: Libraries :: Python Modules
Classifier: License :: OSI Approved :: MIT License
Classifier: Programming Language :: Python
Classifier: Programming Language :: Python :: 3 :: Only
Classifier: Programming Language :: Python :: 3.11
Classifier: Operating System :: OS Independent
Classifier: Intended Audience :: Developers
Classifier: Natural Language :: English
Classifier: Typing :: Typed
Requires-Python: >=3.12
License-File: LICENSE
License-File: LICENSE_bundled.md
Requires-Dist: build
Requires-Dist: twine
Requires-Dist: setuptools
Requires-Dist: pytest
Requires-Dist: pytest-asyncio
Requires-Dist: pyserial
Requires-Dist: smbus2
Requires-Dist: telebot
Requires-Dist: aiohttp
Requires-Dist: FastAPI
Requires-Dist: requests
Requires-Dist: uvicorn
Requires-Dist: numpy
Requires-Dist: PyQt5
Requires-Dist: PyYAML
Requires-Dist: pydantic
Requires-Dist: bs4
Requires-Dist: gitpython
